dlogs/main.py
dlogs-1.0.1.dist-info/licenses/LICENSE
dlogs-1.0.1.dist-info/METADATA
dlogs-1.0.1.dist-info/WHEEL
dlogs-1.0.1.dist-info/entry_points.txt
dlogs-1.0.1.dist-info/top_level.txt
dlogs-1.0.1.dist-info/RECORD
