Metadata-Version: 2.4
Name: dlogs
Version: 1.0.1
Summary: A tool for analyzing and reporting on log files.
Author-email: Aiko Sora <altairteam@bk.ru>
License-Expression: MIT
Project-URL: Repository, https://github.com/quirkink/dlogs
Project-URL: Homepage, https://github.com/quirkink/dlogs
Project-URL: Issues, https://github.com/quirkink/dlogs/issues
Requires-Python: >=3.11
License-File: LICENSE
Dynamic: license-file
